Metadata-Version: 1.0
Name: distributions-metric
Version: 1.0
Summary: Gaussian and Binomial distributions
Home-page: UNKNOWN
Author: Yu Zheng
Author-email: UNKNOWN
License: UNKNOWN
Platform: UNKNOWN
